forecast_solar/__init__.py
forecast_solar/exceptions.py
forecast_solar/forecast_solar.py
forecast_solar/models.py
forecast_solar/py.typed
forecast_solar-4.2.0.dist-info/LICENSE
forecast_solar-4.2.0.dist-info/METADATA
forecast_solar-4.2.0.dist-info/WHEEL
forecast_solar-4.2.0.dist-info/RECORD
