Metadata-Version: 2.3
Name: forecast-solar
Version: 4.2.0
Summary: Asynchronous Python client for getting forecast solar information
License: MIT
Keywords: forecast,solar,power,energy,api,async,client
Author: Klaas Schoute
Author-email: <hello@student-techlife.com>
Maintainer: Klaas Schoute
Maintainer-email: <hello@student-techlife.com>
Requires-Python: >=3.11
Classifier: Framework :: AsyncIO
Classifier: Intended Audience :: Developers
Classifier: License :: OSI Approved :: MIT License
Classifier: Natural Language :: English
Classifier: Programming Language :: Python :: 3.11
Classifier: Programming Language :: Python :: 3.12
Classifier: Programming Language :: Python :: 3.13
Classifier: Programming Language :: Python :: 3
Classifier: Topic :: Software Development :: Libraries :: Python Modules
Requires-Dist: aiohttp (>=3.0.0)
Requires-Dist: yarl (>=1.6.0)
Project-URL: Bug Tracker, https://github.com/home-assistant-libs/forecast_solar/issues
Project-URL: Changelog, https://github.com/home-assistant-libs/forecast_solar/releases
Project-URL: Documentation, https://github.com/home-assistant-libs/forecast_solar
Project-URL: Homepage, https://github.com/home-assistant-libs/forecast_solar
Project-URL: Repository, https://github.com/home-assistant-libs/forecast_solar
